{
  "fullNodeVersion": "v2.5.0",
  "compilerOptionsUsed": {
    "ignoreUnusedConstantsWarnings": false,
    "ignoreUnusedVariablesWarnings": false,
    "ignoreUnusedFieldsWarnings": false,
    "ignoreUnusedPrivateFunctionsWarnings": false,
    "ignoreUpdateFieldsCheckWarnings": false,
    "ignoreCheckExternalCallerWarnings": false
  },
  "infos": {
    "Buy": {
      "sourceFile": "buyTicket.ral",
      "sourceCodeHash": "3293f95ae2db62cd3810fefb2c68bff10f6743a5766587f5519744850d376330",
      "bytecodeDebugPatch": "",
      "codeHashDebug": "",
      "warnings": []
    },
    "Close": {
      "sourceFile": "poolState.ral",
      "sourceCodeHash": "9408d236a13cfbcfe57a0bb4a54f576a504a714f9c1d393ce7779ab62362b5d7",
      "bytecodeDebugPatch": "",
      "codeHashDebug": "",
      "warnings": []
    },
    "Destroy": {
      "sourceFile": "poolState.ral",
      "sourceCodeHash": "9408d236a13cfbcfe57a0bb4a54f576a504a714f9c1d393ce7779ab62362b5d7",
      "bytecodeDebugPatch": "",
      "codeHashDebug": "",
      "warnings": []
    },
    "Distribute": {
      "sourceFile": "distribute.ral",
      "sourceCodeHash": "ec7f34f4af9a55a7138df4215f041844bef6be5dfbe30a3ece83a51ad3499460",
      "bytecodeDebugPatch": "",
      "codeHashDebug": "",
      "warnings": []
    },
    "Open": {
      "sourceFile": "poolState.ral",
      "sourceCodeHash": "9408d236a13cfbcfe57a0bb4a54f576a504a714f9c1d393ce7779ab62362b5d7",
      "bytecodeDebugPatch": "",
      "codeHashDebug": "",
      "warnings": []
    },
    "Walphle": {
      "sourceFile": "waffle.ral",
      "sourceCodeHash": "6919da5dae5858b25ba319555c19ffeb0eacfd6fa60a15e17a1d6cb93b6fea04",
      "bytecodeDebugPatch": "",
      "codeHashDebug": "cf31e9d05754cdf69f34049698dd2bb5a77ec475f75b1cae4b4cfe64e5435ff5",
      "warnings": []
    }
  }
}